{
  "id": "reno9a_rakuten_v16",
  "brandLabel": "OPPO",
  "modelLabel": "Reno9 A (Rakuten Mobile)",
  "summary": "Reno9 A - Android 16",
  "profile": {
    "brand": "OPPO",
    "manufacturer": "OPPO",
    "model": "Reno9 A",
    "productName": "CPH2523",
    "deviceCode": "CPH2523",
    "board": "mt6789",
    "hardware": "mt6789",
    "boardPlatform": "mt6789",
    "buildFingerprint": "OPPO/CPH2523/CPH2523:16/TP1A.260605.003/12665804:user/release-keys",
    "buildId": "TP1A.260605.003",
    "buildDisplayId": "TP1A.260605.003",
    "buildIncremental": "12665804",
    "buildRelease": "16",
    "buildSdk": 36,
    "securityPatch": "2026-06-05",
    "buildDescription": "CPH2523-user 16 TP1A.260605.003 12665804 release-keys",
    "buildFlavor": "CPH2523-user",
    "buildProduct": "CPH2523",
    "buildCharacteristics": "nosdcard",
    "screenWidth": 1080,
    "screenHeight": 2400,
    "screenDensity": 420,
    "operatorAlpha": "rakuten",
    "operatorNumeric": "44011",
    "simCountryIso": "jp",
    "timezone": "Asia/Tokyo",
    "socModel": "Helio G99",
    "socManufacturer": "MediaTek",
    "webglRendering": "Mali-G57 MC2",
    "hardwareConcurrency": 8,
    "deviceMemory": "8GB"
  }
}
